{
  "db_name": "PostgreSQL",
  "query": "\n            SELECT e.id,\n                   e.created_date_time,\n                   e.modification_date_time,\n                   e.program_id,\n                   e.event_name,\n                   e.priority,\n                   e.targets as \"targets:Vec<Target>\",\n                   e.report_descriptors,\n                   e.payload_descriptors,\n                   e.interval_period,\n                   e.intervals,\n                   e.duration\n            FROM event e\n            WHERE ($1::text IS NULL OR e.program_id like $1)\n              -- according to the spec, we MUST only test query params\n              -- against the event that the VEN object (and its resources) have as targets.\n              -- Therefore, $2 is the intersection of the VEN targets and the filter targets.\n              AND ($2::text[] IS NULL OR e.targets @> $2)\n              AND (\n                  -- IF the ven targets have at least one target in common with the event\n                    e.targets && $3\n                        -- or IF the event targets are empty\n                        OR array_length(e.targets, 1) IS NULL\n                  )\n            ORDER BY priority ASC, created_date_time DESC\n            OFFSET $4 LIMIT $5\n            ",
  "describe": {
    "columns": [
      {
        "ordinal": 0,
        "name": "id",
        "type_info": "Text"
      },
      {
        "ordinal": 1,
        "name": "created_date_time",
        "type_info": "Timestamptz"
      },
      {
        "ordinal": 2,
        "name": "modification_date_time",
        "type_info": "Timestamptz"
      },
      {
        "ordinal": 3,
        "name": "program_id",
        "type_info": "Text"
      },
      {
        "ordinal": 4,
        "name": "event_name",
        "type_info": "Text"
      },
      {
        "ordinal": 5,
        "name": "priority",
        "type_info": "Int8"
      },
      {
        "ordinal": 6,
        "name": "targets:Vec<Target>",
        "type_info": "TextArray"
      },
      {
        "ordinal": 7,
        "name": "report_descriptors",
        "type_info": "Jsonb"
      },
      {
        "ordinal": 8,
        "name": "payload_descriptors",
        "type_info": "Jsonb"
      },
      {
        "ordinal": 9,
        "name": "interval_period",
        "type_info": "Jsonb"
      },
      {
        "ordinal": 10,
        "name": "intervals",
        "type_info": "Jsonb"
      },
      {
        "ordinal": 11,
        "name": "duration",
        "type_info": "Text"
      }
    ],
    "parameters": {
      "Left": [
        "Text",
        "TextArray",
        "TextArray",
        "Int8",
        "Int8"
      ]
    },
    "nullable": [
      false,
      false,
      false,
      false,
      true,
      true,
      false,
      true,
      true,
      true,
      false,
      true
    ]
  },
  "hash": "5017cbbc01f9ebdaaa79cbd24c948b44216776b053d982b55b3adfe938eb956b"
}
