{
  "db_name": "PostgreSQL",
  "query": "\n            SELECT DISTINCT\n                r.id AS \"id!\",\n                r.created_date_time AS \"created_date_time!\",\n                r.modification_date_time AS \"modification_date_time!\",\n                r.resource_name AS \"resource_name!\",\n                r.ven_id AS \"ven_id!\",\n                r.attributes,\n                r.targets\n            FROM resource r\n            WHERE r.ven_id = $1\n                AND ($2::text IS NULL OR r.resource_name = $2)\n                AND ($3::text[] IS NULL OR r.targets ?| $3)\n            ORDER BY r.created_date_time\n            OFFSET $4 LIMIT $5\n            ",
  "describe": {
    "columns": [
      {
        "ordinal": 0,
        "name": "id!",
        "type_info": "Text"
      },
      {
        "ordinal": 1,
        "name": "created_date_time!",
        "type_info": "Timestamptz"
      },
      {
        "ordinal": 2,
        "name": "modification_date_time!",
        "type_info": "Timestamptz"
      },
      {
        "ordinal": 3,
        "name": "resource_name!",
        "type_info": "Text"
      },
      {
        "ordinal": 4,
        "name": "ven_id!",
        "type_info": "Text"
      },
      {
        "ordinal": 5,
        "name": "attributes",
        "type_info": "Jsonb"
      },
      {
        "ordinal": 6,
        "name": "targets",
        "type_info": "Jsonb"
      }
    ],
    "parameters": {
      "Left": [
        "Text",
        "Text",
        "TextArray",
        "Int8",
        "Int8"
      ]
    },
    "nullable": [
      false,
      false,
      false,
      false,
      false,
      true,
      true
    ]
  },
  "hash": "ba848aff53d2bdd0c97220a7d1c8e8f2602deb5a17ef0cce2d9b3fc45ca4d225"
}
